admin_torch/__init__.py
admin_torch/admin.py
admin_torch-0.1.0.dist-info/LICENSE
admin_torch-0.1.0.dist-info/METADATA
admin_torch-0.1.0.dist-info/WHEEL
admin_torch-0.1.0.dist-info/top_level.txt
admin_torch-0.1.0.dist-info/RECORD
