Metadata-Version: 2.1
Name: admin-torch
Version: 0.1.0
Summary: Plug-in-and-Play Toolbox for Stablizing Transformer Training
Home-page: https://github.com/microsoft/admin-torch
Author: Lucas Liu
Author-email: llychinalz@gmail.com
License: Apache License 2.0
Platform: UNKNOWN
Classifier: Development Status :: 2 - Pre-Alpha
Classifier: Intended Audience :: Developers
Classifier: Natural Language :: English
Classifier: Programming Language :: Python :: 3.7
Classifier: Programming Language :: Python :: 3.8
Classifier: Programming Language :: Python :: 3.9
License-File: LICENSE
Requires-Dist: torch
